{
  "video_id": "1kEoS9WwpmA",
  "title": "Benedict Cumberbatch Performs \"I'm a Little Teapot\" // Omaze",
  "es": 0,
  "json": [
    {
      "index": 1,
      "start_time": 800.0,
      "end_time": 8390.0,
      "text": "[vocal exercises]"
    },
    {
      "index": 2,
      "start_time": 8390.0,
      "end_time": 9959.0,
      "text": "Benedict Cumberbatch met a feminist lumberjack."
    },
    {
      "index": 3,
      "start_time": 9960.0,
      "end_time": 11260.0,
      "text": "Benedict Cumberbatch met a feminist..."
    },
    {
      "index": 4,
      "start_time": 11260.0,
      "end_time": 11940.0,
      "text": "Oh, hello!"
    },
    {
      "index": 5,
      "start_time": 11940.0,
      "end_time": 12899.0,
      "text": "[clears throat]"
    },
    {
      "index": 6,
      "start_time": 12900.0,
      "end_time": 14640.0,
      "text": "You caught me doing my standard"
    },
    {
      "index": 7,
      "start_time": 14640.0,
      "end_time": 16140.0,
      "text": "vocal warm-up exercises."
    },
    {
      "index": 8,
      "start_time": 17760.0,
      "end_time": 19600.0,
      "text": "Actually, I'm glad you're here"
    },
    {
      "index": 9,
      "start_time": 19600.0,
      "end_time": 20990.0,
      "text": "because I've got a question for you."
    },
    {
      "index": 10,
      "start_time": 20990.0,
      "end_time": 21840.0,
      "text": "Yes, you."
    },
    {
      "index": 11,
      "start_time": 21840.0,
      "end_time": 22740.0,
      "text": "You who aren't paying attention."
    },
    {
      "index": 12,
      "start_time": 22740.0,
      "end_time": 23340.0,
      "text": "Pay attention."
    },
    {
      "index": 13,
      "start_time": 23340.0,
      "end_time": 24540.0,
      "text": "I suppose I should explain."
    },
    {
      "index": 14,
      "start_time": 24540.0,
      "end_time": 26780.0,
      "text": "I am Benedict Cumberbatch, actor,"
    },
    {
      "index": 15,
      "start_time": 26780.0,
      "end_time": 28540.0,
      "text": "and I'm teaming up with Omaze"
    },
    {
      "index": 16,
      "start_time": 28540.0,
      "end_time": 31400.0,
      "text": "to fly you and a friend out to Los Angeles"
    },
    {
      "index": 17,
      "start_time": 31400.0,
      "end_time": 33960.0,
      "text": "to attend the world premiere of my next student film,"
    },
    {
      "index": 18,
      "start_time": 33960.0,
      "end_time": 36220.0,
      "text": "[movie trailer voice]: Avengers: Infinity War!"
    },
    {
      "index": 19,
      "start_time": 36220.0,
      "end_time": 36900.0,
      "text": "Which, for those of you who don't speak American accents,"
    },
    {
      "index": 20,
      "start_time": 38140.0,
      "end_time": 40180.0,
      "text": "is Avengers: Infinity War."
    },
    {
      "index": 21,
      "start_time": 40180.0,
      "end_time": 43120.0,
      "text": "And seeing as, well, we'll be in LA at the same time,"
    },
    {
      "index": 22,
      "start_time": 43120.0,
      "end_time": 45379.0,
      "text": "it's the perfect opportunity for us to meet"
    },
    {
      "index": 23,
      "start_time": 45380.0,
      "end_time": 47660.0,
      "text": "for tea and delightful conversation."
    },
    {
      "index": 24,
      "start_time": 47660.0,
      "end_time": 50480.0,
      "text": "\"What will it be like to have tea with an actor?\" you ask."
    },
    {
      "index": 25,
      "start_time": 50480.0,
      "end_time": 53239.0,
      "text": "Well, I've prepared a short monologue for you"
    },
    {
      "index": 26,
      "start_time": 53240.0,
      "end_time": 55100.0,
      "text": "that should make things quite clear."
    },
    {
      "index": 27,
      "start_time": 60940.0,
      "end_time": 62239.0,
      "text": "And go, actor."
    },
    {
      "index": 28,
      "start_time": 65280.0,
      "end_time": 71360.0,
      "text": "I'm a little teapot, short and stout."
    },
    {
      "index": 29,
      "start_time": 71360.0,
      "end_time": 78460.0,
      "text": "This is my handle, and this is my spout."
    },
    {
      "index": 30,
      "start_time": 78460.0,
      "end_time": 83320.0,
      "text": "When I get all steamed up, hear me shout,"
    },
    {
      "index": 31,
      "start_time": 83320.0,
      "end_time": 90839.0,
      "text": "“Tip me over and pour me out.”"
    },
    {
      "index": 32,
      "start_time": 93780.0,
      "end_time": 94920.0,
      "text": "Release,"
    },
    {
      "index": 33,
      "start_time": 94920.0,
      "end_time": 96900.0,
      "text": "and I'm back. Hi."
    },
    {
      "index": 34,
      "start_time": 96900.0,
      "end_time": 98260.0,
      "text": "It'll be exactly like that."
    },
    {
      "index": 35,
      "start_time": 98260.0,
      "end_time": 100660.0,
      "text": "But the best part of this is that every donation"
    },
    {
      "index": 36,
      "start_time": 100660.0,
      "end_time": 102130.0,
      "text": "benefits The GEANCO Foundation."
    },
    {
      "index": 37,
      "start_time": 102130.0,
      "end_time": 104460.0,
      "text": "Their mission is to save and transform"
    },
    {
      "index": 38,
      "start_time": 104460.0,
      "end_time": 106640.0,
      "text": "the lives of the poor and vulnerable in Africa,"
    },
    {
      "index": 39,
      "start_time": 106640.0,
      "end_time": 108310.0,
      "text": "and they're a charity very dear to my heart."
    },
    {
      "index": 40,
      "start_time": 108310.0,
      "end_time": 110400.0,
      "text": "So for your chance to help with that great cause,"
    },
    {
      "index": 41,
      "start_time": 110400.0,
      "end_time": 111620.0,
      "text": "to have tea with me"
    },
    {
      "index": 42,
      "start_time": 111620.0,
      "end_time": 113720.0,
      "text": "and to win two, not one, but two tickets"
    },
    {
      "index": 43,
      "start_time": 113720.0,
      "end_time": 115860.0,
      "text": "to the premiere of Avengers: Infinity War,"
    },
    {
      "index": 44,
      "start_time": 115860.0,
      "end_time": 121400.0,
      "text": "click the link, or go to omaze.com/benedict."
    },
    {
      "index": 45,
      "start_time": 121400.0,
      "end_time": 122900.0,
      "text": "Benedict."
    },
    {
      "index": 46,
      "start_time": 122900.0,
      "end_time": 124180.0,
      "text": "Just once. I was saying that for clarity."
    },
    {
      "index": 47,
      "start_time": 124180.0,
      "end_time": 125460.0,
      "text": "Now, if you'll excuse me,"
    },
    {
      "index": 48,
      "start_time": 125460.0,
      "end_time": 127399.0,
      "text": "I have a little bit more work to do on my warm- up, so..."
    },
    {
      "index": 49,
      "start_time": 127400.0,
      "end_time": 128560.0,
      "text": "Benedict Cumberbatch."
    },
    {
      "index": 50,
      "start_time": 128560.0,
      "end_time": 129699.0,
      "text": "Benedict Cumberbatch."
    },
    {
      "index": 51,
      "start_time": 129699.00000000001,
      "end_time": 132140.0,
      "text": "Benedict Cumberbatch broke a delicate luggage rack."
    },
    {
      "index": 52,
      "start_time": 132140.0,
      "end_time": 133559.0,
      "text": "Benedict Cumberbatch broke a delicate luggage rack."
    },
    {
      "index": 53,
      "start_time": 133560.0,
      "end_time": 136500.0,
      "text": "Benedict Cumberbatch broke a delicate luggage rack."
    },
    {
      "index": 54,
      "start_time": 136500.0,
      "end_time": 137560.0,
      "text": "See you in LA."
    }
  ]
}