{
  "video_id": "T-sy6rPJBj4",
  "title": "The Science Behind Climate Change (Documentary)",
  "es": 0,
  "json": [
    {
      "index": 1,
      "start_time": 24500.0,
      "end_time": 26300.0,
      "text": "What is global warming?"
    },
    {
      "index": 2,
      "start_time": 28500.0,
      "end_time": 31500.0,
      "text": "How did it start?"
    },
    {
      "index": 3,
      "start_time": 32200.000000000004,
      "end_time": 33500.0,
      "text": "How will it continue?"
    },
    {
      "index": 4,
      "start_time": 38080.0,
      "end_time": 40080.0,
      "text": "What will happen to humanity?"
    },
    {
      "index": 5,
      "start_time": 42600.0,
      "end_time": 46340.0,
      "text": "Will one day we be gone due to our own ignorance?"
    },
    {
      "index": 6,
      "start_time": 72700.0,
      "end_time": 78860.0,
      "text": "Global Warming is the continuing rise in the average temperature of Earth's climate system"
    },
    {
      "index": 7,
      "start_time": 80300.0,
      "end_time": 85700.0,
      "text": "Through the sudden use of factories, gas consuming cars and and other ambitions from fossil fuels"
    },
    {
      "index": 8,
      "start_time": 85700.0,
      "end_time": 90720.0,
      "text": "the Earth's temperature has rapidly increased since the beginning of the industrial age."
    },
    {
      "index": 9,
      "start_time": 92960.0,
      "end_time": 95200.0,
      "text": "Global warming is a natural event"
    },
    {
      "index": 10,
      "start_time": 95800.0,
      "end_time": 98020.0,
      "text": "but is being majorly contributed to by humans."
    },
    {
      "index": 11,
      "start_time": 98440.0,
      "end_time": 103720.0,
      "text": "Today, the quality of the atmosphere has been irreversibly depleted over time"
    },
    {
      "index": 12,
      "start_time": 104320.0,
      "end_time": 108060.0,
      "text": "and if nothing is done about it, the Earth will ultimately swelter"
    },
    {
      "index": 13,
      "start_time": 108440.0,
      "end_time": 111120.0,
      "text": "Americans are noticing changes all around them already."
    },
    {
      "index": 14,
      "start_time": 112540.0,
      "end_time": 114540.0,
      "text": "Summers are longer and hotter"
    },
    {
      "index": 15,
      "start_time": 114920.0,
      "end_time": 120640.0,
      "text": "An extended periods of unusual heat last longer than any living American has ever experienced."
    },
    {
      "index": 16,
      "start_time": 122100.0,
      "end_time": 124380.0,
      "text": "Winters are generally shorter and warmer."
    },
    {
      "index": 17,
      "start_time": 126340.0,
      "end_time": 128220.0,
      "text": "Rain comes in heavier downpours,"
    },
    {
      "index": 18,
      "start_time": 128759.99999999999,
      "end_time": 130899.99999999999,
      "text": "tropical storms are much more intense,"
    },
    {
      "index": 19,
      "start_time": 130900.0,
      "end_time": 133320.0,
      "text": "more destructive, and more frequent."
    },
    {
      "index": 20,
      "start_time": 137200.0,
      "end_time": 141320.0,
      "text": "Residence of some costal cities see their streets flood more regularly"
    },
    {
      "index": 21,
      "start_time": 141320.0,
      "end_time": 143680.0,
      "text": "during storms and high tides."
    },
    {
      "index": 22,
      "start_time": 144560.0,
      "end_time": 148560.0,
      "text": "And the cities near large rivers also experience more flooding,"
    },
    {
      "index": 23,
      "start_time": 148680.0,
      "end_time": 151100.0,
      "text": "especially in the midwest and northeast."
    },
    {
      "index": 24,
      "start_time": 152480.0,
      "end_time": 153960.0,
      "text": "So how does this happen?"
    },
    {
      "index": 25,
      "start_time": 154760.0,
      "end_time": 158720.0,
      "text": "It is through something called \"the enhanced greenhouse effect\""
    },
    {
      "index": 26,
      "start_time": 158720.0,
      "end_time": 161220.0,
      "text": "which is the key ingredient of global warming."
    },
    {
      "index": 27,
      "start_time": 162180.0,
      "end_time": 168260.0,
      "text": "Greenhouse gasses include water vapor, carbon dioxide, methane, nitrous oxide and ozone."
    },
    {
      "index": 28,
      "start_time": 169780.0,
      "end_time": 172700.0,
      "text": "Greenhouse gasses help regulate the temperature of the Earth."
    },
    {
      "index": 29,
      "start_time": 173180.0,
      "end_time": 178140.0,
      "text": "The raise of the sun warm the Earth and the Earth reflects the radiated heat outwards."
    },
    {
      "index": 30,
      "start_time": 178600.0,
      "end_time": 182220.0,
      "text": "Greenhouse gasses prevent this heat from escaping from the surface of the earth."
    },
    {
      "index": 31,
      "start_time": 182940.0,
      "end_time": 184180.0,
      "text": "Without these gasses,"
    },
    {
      "index": 32,
      "start_time": 184520.0,
      "end_time": 187620.0,
      "text": "the temperature of the earth would be unbearably colder."
    },
    {
      "index": 33,
      "start_time": 188960.0,
      "end_time": 192520.0,
      "text": "It is the sun that provides our planet with warmth and light,"
    },
    {
      "index": 34,
      "start_time": 193080.0,
      "end_time": 196500.0,
      "text": "but the amount of energy that the Earth receives from the sun varies."
    },
    {
      "index": 35,
      "start_time": 197140.0,
      "end_time": 201420.0,
      "text": "Throughout the Earths existence the Earth has gradually changed its orbit around the sun."
    },
    {
      "index": 36,
      "start_time": 201660.0,
      "end_time": 207820.0,
      "text": "And with each orbit, the patterns of the energy that the Earth receives are different from each other."
    },
    {
      "index": 37,
      "start_time": 208140.0,
      "end_time": 212440.0,
      "text": "These changes have contributed to dramatic shfits in Earths climate."
    },
    {
      "index": 38,
      "start_time": 214480.0,
      "end_time": 217700.0,
      "text": "The suns radiation comes in the form of light waves"
    },
    {
      "index": 39,
      "start_time": 217940.0,
      "end_time": 218960.0,
      "text": "heating up the Earth."
    },
    {
      "index": 40,
      "start_time": 219720.0,
      "end_time": 224820.0,
      "text": "Some of the radiation that is absorbed and warmths the Earth is reradiated back into space"
    },
    {
      "index": 41,
      "start_time": 224820.0,
      "end_time": 226500.0,
      "text": "in the form of infrared waves."
    },
    {
      "index": 42,
      "start_time": 227460.0,
      "end_time": 232280.0,
      "text": "But some of the infrared radiation is trapped by the atmosphere and held inside it."
    },
    {
      "index": 43,
      "start_time": 233620.0,
      "end_time": 234820.0,
      "text": "So the problem is,"
    },
    {
      "index": 44,
      "start_time": 234820.0,
      "end_time": 241820.0,
      "text": "that the atmosphere is continuing to consist of more and more carbon dioxide and greenhouse gasses due to human kind,"
    },
    {
      "index": 45,
      "start_time": 242820.0,
      "end_time": 246960.0,
      "text": "And therefore making the radiation from the sun become trapped on Earth"
    },
    {
      "index": 46,
      "start_time": 247300.0,
      "end_time": 249140.0,
      "text": "and heats up the planet."
    },
    {
      "index": 47,
      "start_time": 251060.0,
      "end_time": 253640.0,
      "text": "Since the beginning of the industrial revolution,"
    },
    {
      "index": 48,
      "start_time": 254020.0,
      "end_time": 258720.0,
      "text": "nitrous oxide, which is used in fertilizer, has increased 18%,"
    },
    {
      "index": 49,
      "start_time": 259420.00000000003,
      "end_time": 263060.0,
      "text": "carbon dioxide from fossil fuel combustion 39 %,"
    },
    {
      "index": 50,
      "start_time": 263260.0,
      "end_time": 265440.0,
      "text": "and methane 148%."
    },
    {
      "index": 51,
      "start_time": 265860.0,
      "end_time": 270600.0,
      "text": "By adding more greenhouse gasses, we have altered the natural cycle of the atmosphere"
    },
    {
      "index": 52,
      "start_time": 271180.0,
      "end_time": 274320.0,
      "text": "making it harder for radiation to escape to outer space."
    },
    {
      "index": 53,
      "start_time": 279280.0,
      "end_time": 284480.0,
      "text": "Gasses in the atmosphere absorb both shortwave solar radiation and low wave infrared radiation"
    },
    {
      "index": 54,
      "start_time": 284480.0,
      "end_time": 287120.0,
      "text": "in which this radiant energy warms the atmosphere."
    },
    {
      "index": 55,
      "start_time": 287420.0,
      "end_time": 291360.0,
      "text": "When too much carbon dioxide is put up into the atmosphere,"
    },
    {
      "index": 56,
      "start_time": 291360.0,
      "end_time": 293020.0,
      "text": "that disrupts the balance,"
    },
    {
      "index": 57,
      "start_time": 293420.0,
      "end_time": 297020.0,
      "text": "like super saturating and already existing solution."
    },
    {
      "index": 58,
      "start_time": 297920.0,
      "end_time": 303460.0,
      "text": "For example, carbon dioxide already makes up 0.03% of the atmosphere"
    },
    {
      "index": 59,
      "start_time": 303800.0,
      "end_time": 306040.0,
      "text": "in which is steadily increasing."
    },
    {
      "index": 60,
      "start_time": 307420.0,
      "end_time": 313560.0,
      "text": "If you put sugar into water, there is a limit to which the sugar and water will no longer mix."
    },
    {
      "index": 61,
      "start_time": 314340.0,
      "end_time": 315380.0,
      "text": "The same happens here,"
    },
    {
      "index": 62,
      "start_time": 315420.0,
      "end_time": 317820.0,
      "text": "if you put too much carbon dioxide up"
    },
    {
      "index": 63,
      "start_time": 318300.0,
      "end_time": 322700.0,
      "text": "it absorbs infrared radiation depending on its vibration of its bonds."
    },
    {
      "index": 64,
      "start_time": 323740.0,
      "end_time": 329920.0,
      "text": "We'll overall increase the amount of energy, and we'll ultimately increase the overall temperature."
    },
    {
      "index": 65,
      "start_time": 331600.0,
      "end_time": 334880.0,
      "text": "Part of this is due to the kinetic molecular theory,"
    },
    {
      "index": 66,
      "start_time": 335280.0,
      "end_time": 338060.0,
      "text": "meaning more energy causes further vibration,"
    },
    {
      "index": 67,
      "start_time": 338360.0,
      "end_time": 342380.0,
      "text": "which causes the gasses to start bouncing off of each other more quickly."
    },
    {
      "index": 68,
      "start_time": 343440.0,
      "end_time": 347160.0,
      "text": "Basically, the overall understanding is that there is a rise"
    },
    {
      "index": 69,
      "start_time": 347600.0,
      "end_time": 351160.0,
      "text": "in 0.5 degrees to 1 degrees centigrade."
    },
    {
      "index": 70,
      "start_time": 353560.0,
      "end_time": 357200.0,
      "text": "The quantity insists of aerosols and molecules in the atmosphere"
    },
    {
      "index": 71,
      "start_time": 357200.0,
      "end_time": 359460.0,
      "text": "affect the way that they scatter radiation."
    },
    {
      "index": 72,
      "start_time": 360080.0,
      "end_time": 363560.0,
      "text": "This differences is easy to observe in the visible part of the spectrum."
    },
    {
      "index": 73,
      "start_time": 364760.0,
      "end_time": 366200.0,
      "text": "Our sky appears blue,"
    },
    {
      "index": 74,
      "start_time": 366940.0,
      "end_time": 368860.0,
      "text": "because the white sunlight coming towards the Earth"
    },
    {
      "index": 75,
      "start_time": 368860.0,
      "end_time": 372600.0,
      "text": "is scattered by the nitrogen and oxygen molecules in the atmosphere."
    },
    {
      "index": 76,
      "start_time": 373620.0,
      "end_time": 377180.0,
      "text": "This process is called the rayleigh scattering effect."
    },
    {
      "index": 77,
      "start_time": 380280.0,
      "end_time": 384520.0,
      "text": "The molecules of these gasses interfere with incoming sunlight."
    },
    {
      "index": 78,
      "start_time": 385020.0,
      "end_time": 388580.0,
      "text": "The shortwave length, blue light, is more strongly affected"
    },
    {
      "index": 79,
      "start_time": 388580.0,
      "end_time": 390800.0,
      "text": "and is scattered in all directions."
    },
    {
      "index": 80,
      "start_time": 391300.0,
      "end_time": 395560.0,
      "text": "While the longer wave length, green and red light, is able to pass straight through."
    },
    {
      "index": 81,
      "start_time": 396500.0,
      "end_time": 397640.0,
      "text": "As you look at the sky,"
    },
    {
      "index": 82,
      "start_time": 398120.0,
      "end_time": 399780.0,
      "text": "you are seeing the scattered light."
    },
    {
      "index": 83,
      "start_time": 400100.0,
      "end_time": 401660.0,
      "text": "Therefore the sky looks blue."
    },
    {
      "index": 84,
      "start_time": 402640.0,
      "end_time": 405280.0,
      "text": "So if the atmosphere scatters more blue light than red light,"
    },
    {
      "index": 85,
      "start_time": 405860.0,
      "end_time": 407940.0,
      "text": "then you may wonder why sunsets look red."
    },
    {
      "index": 86,
      "start_time": 408540.0,
      "end_time": 409040.0,
      "text": "First,"
    },
    {
      "index": 87,
      "start_time": 409620.0,
      "end_time": 410840.0,
      "text": "when you look at the sunset,"
    },
    {
      "index": 88,
      "start_time": 411160.0,
      "end_time": 413960.0,
      "text": "you are looking toward the sun, not away from it."
    },
    {
      "index": 89,
      "start_time": 414520.0,
      "end_time": 417060.0,
      "text": "So while all of the blue light has been scattered away,"
    },
    {
      "index": 90,
      "start_time": 417380.0,
      "end_time": 421280.0,
      "text": "you're looking at the redder light that passes straight through the atmosphere to your eyes."
    },
    {
      "index": 91,
      "start_time": 422300.0,
      "end_time": 422800.0,
      "text": "Secondly,"
    },
    {
      "index": 92,
      "start_time": 423220.0,
      "end_time": 424580.0,
      "text": "the sun is lower in the sky,"
    },
    {
      "index": 93,
      "start_time": 424880.0,
      "end_time": 427880.0,
      "text": "so the light is forced to travel through much more of the atmosphere."
    },
    {
      "index": 94,
      "start_time": 428220.0,
      "end_time": 432260.0,
      "text": "In the process, it also passes through much more water vapor and dust."
    },
    {
      "index": 95,
      "start_time": 432940.0,
      "end_time": 436140.0,
      "text": "Water vapor and dust both absorb the shortwave length,"
    },
    {
      "index": 96,
      "start_time": 436140.0,
      "end_time": 438420.0,
      "text": "blue light, while allowing the longer wave length,"
    },
    {
      "index": 97,
      "start_time": 438420.0,
      "end_time": 441120.0,
      "text": "red light, to pass straight through to your eyes."
    },
    {
      "index": 98,
      "start_time": 441760.0,
      "end_time": 444740.0,
      "text": "Different molecules absorb different wave lengths of light,"
    },
    {
      "index": 99,
      "start_time": 444740.0,
      "end_time": 446840.0,
      "text": "making a unique pattern in the spectrum"
    },
    {
      "index": 100,
      "start_time": 446840.0,
      "end_time": 450780.0,
      "text": "like a fingerprint that we can use to identify the molecules."
    },
    {
      "index": 101,
      "start_time": 456800.0,
      "end_time": 458440.0,
      "text": "As mentioned before,"
    },
    {
      "index": 102,
      "start_time": 458720.0,
      "end_time": 461880.0,
      "text": "one of the largest and most detrimental factors of global warming"
    },
    {
      "index": 103,
      "start_time": 461880.0,
      "end_time": 466920.0,
      "text": "is the increased melting of permanent ice sheets and glaciers all over the globe."
    },
    {
      "index": 104,
      "start_time": 468620.0,
      "end_time": 473860.0,
      "text": "From 1978 to 2004, perennial sea ice cover in the arctic"
    },
    {
      "index": 105,
      "start_time": 473860.0,
      "end_time": 477260.0,
      "text": "declined by 7.8% each decade."
    },
    {
      "index": 106,
      "start_time": 477960.0,
      "end_time": 479700.0,
      "text": "If these trends continue,"
    },
    {
      "index": 107,
      "start_time": 480060.0,
      "end_time": 484620.0,
      "text": "late summer sea ice could disappear from the arctic as early as 2030."
    },
    {
      "index": 108,
      "start_time": 487620.0,
      "end_time": 491940.0,
      "text": "Palio climate scientists can learn a lot about the Earths past climate"
    },
    {
      "index": 109,
      "start_time": 491940.0,
      "end_time": 493580.0,
      "text": "by looking at the air in the ice,"
    },
    {
      "index": 110,
      "start_time": 494100.0,
      "end_time": 497020.0,
      "text": "all by analyzing what geochemical proxies"
    },
    {
      "index": 111,
      "start_time": 497500.0,
      "end_time": 500220.0,
      "text": "that are contained in the air bubbles of  the ice."
    },
    {
      "index": 112,
      "start_time": 502280.0,
      "end_time": 503640.0,
      "text": "To analyze this ice,"
    },
    {
      "index": 113,
      "start_time": 504240.0,
      "end_time": 507460.0,
      "text": "scientists set the ice cores onto a continuous melter"
    },
    {
      "index": 114,
      "start_time": 507460.0,
      "end_time": 509300.0,
      "text": "which is just like a hotplate,"
    },
    {
      "index": 115,
      "start_time": 509740.0,
      "end_time": 511900.0,
      "text": "and it melts the ice core layer after layer."
    },
    {
      "index": 116,
      "start_time": 512620.0,
      "end_time": 516720.0,
      "text": "As the water is produced, and the included air bubbles are released,"
    },
    {
      "index": 117,
      "start_time": 516919.99999999994,
      "end_time": 518779.99999999994,
      "text": "it is brought through various instruments,"
    },
    {
      "index": 118,
      "start_time": 519240.0,
      "end_time": 523480.0,
      "text": "such as a mass spectrometer for an analysis of the chemical composition"
    },
    {
      "index": 119,
      "start_time": 523940.00000000006,
      "end_time": 526260.0,
      "text": "of the water and the air included."
    },
    {
      "index": 120,
      "start_time": 527500.0,
      "end_time": 532080.0,
      "text": "These scientists are specifically looking for properties of the water or air"
    },
    {
      "index": 121,
      "start_time": 532560.0,
      "end_time": 535600.0,
      "text": "that can reveal what the environment was like when the snow fell"
    },
    {
      "index": 122,
      "start_time": 535600.0,
      "end_time": 537580.0,
      "text": "on the ice sheet they are probing."
    },
    {
      "index": 123,
      "start_time": 539300.0,
      "end_time": 542860.0,
      "text": "This record makes the conclusion that the last 100 years"
    },
    {
      "index": 124,
      "start_time": 542900.0,
      "end_time": 546980.0,
      "text": "of manmade atmospheric alterations have had a profound affect on the"
    },
    {
      "index": 125,
      "start_time": 546980.0,
      "end_time": 550180.0,
      "text": "average temperature of the Earths atmosphere evident."
    },
    {
      "index": 126,
      "start_time": 551260.0,
      "end_time": 553520.0,
      "text": "In the ice cores there are little bubbles."
    },
    {
      "index": 127,
      "start_time": 553520.0,
      "end_time": 558360.0,
      "text": "And those individual bubbles contain a real sample of the atmosphere through time."
    },
    {
      "index": 128,
      "start_time": 559280.0,
      "end_time": 562980.0,
      "text": "Scientists can then release that air and measure the greenhouse gasses."
    },
    {
      "index": 129,
      "start_time": 563720.0,
      "end_time": 566740.0,
      "text": "It is almost like taking the DNA of the atmosphere."
    },
    {
      "index": 130,
      "start_time": 567540.0,
      "end_time": 571180.0,
      "text": "This record of past climate generated by ice core analysis"
    },
    {
      "index": 131,
      "start_time": 571180.0,
      "end_time": 574260.0,
      "text": "is essential to the global warming discussion."
    },
    {
      "index": 132,
      "start_time": 575400.0,
      "end_time": 580480.0,
      "text": "It creates a benchmark for the pattern of natural variability in the climate record."
    },
    {
      "index": 133,
      "start_time": 580480.0,
      "end_time": 586000.0,
      "text": "And thereby, proves the existence of the manmade enhanced greenhouse effect."
    },
    {
      "index": 134,
      "start_time": 586540.0,
      "end_time": 591380.0,
      "text": "As palio climate scientists are struggling to record as much as they can from the ancient ice,"
    },
    {
      "index": 135,
      "start_time": 591380.0,
      "end_time": 593160.0,
      "text": "they are quickly disappearing."
    },
    {
      "index": 136,
      "start_time": 593380.0,
      "end_time": 596960.0,
      "text": "Nearly all icecaps and glaciers in the world have experienced a net loss"
    },
    {
      "index": 137,
      "start_time": 596960.0,
      "end_time": 599060.0,
      "text": "of volume every year for decades."
    },
    {
      "index": 138,
      "start_time": 599340.0,
      "end_time": 602480.0,
      "text": "Sight light and photographic records show this in great detail."
    },
    {
      "index": 139,
      "start_time": 602960.0,
      "end_time": 606540.0,
      "text": "One of the places where this is most evident is in the arctic ocean"
    },
    {
      "index": 140,
      "start_time": 606540.0,
      "end_time": 610000.0,
      "text": "where the arctics sea ice extent is declining dramatically every summer."
    },
    {
      "index": 141,
      "start_time": 610380.0,
      "end_time": 614340.0,
      "text": "Snow nearly accesses a mirror reflecting the solor radiation back in the space,"
    },
    {
      "index": 142,
      "start_time": 614920.0,
      "end_time": 618800.0,
      "text": "but when the ice is gone and the sailor radiation hits liquid water instead,"
    },
    {
      "index": 143,
      "start_time": 619240.0,
      "end_time": 624300.0,
      "text": "then most of the energy is absorbed by the ocean, and the ocean heats up."
    },
    {
      "index": 144,
      "start_time": 624840.0,
      "end_time": 628520.0,
      "text": "This intern then prevents sea ice from forming"
    },
    {
      "index": 145,
      "start_time": 628540.0,
      "end_time": 631740.0,
      "text": "and therefore by reenforces the warming trend."
    },
    {
      "index": 146,
      "start_time": 632920.0,
      "end_time": 636540.0,
      "text": "Everywhere the ice grows and then every summer the ice would drops."
    },
    {
      "index": 147,
      "start_time": 636840.0,
      "end_time": 642740.0,
      "text": "But in recent years,  summer melting has brought the ice much further back than scientists have ever seen before."
    },
    {
      "index": 148,
      "start_time": 643060.0,
      "end_time": 649360.0,
      "text": "In September of 2012, the arctic sea ice shrank to its lowest extent ever measured."
    },
    {
      "index": 149,
      "start_time": 649740.0,
      "end_time": 654500.0,
      "text": "Loss of arctic sea ice is profoundly important for the globe,"
    },
    {
      "index": 150,
      "start_time": 654500.0,
      "end_time": 655600.0,
      "text": "for a number of reasons."
    },
    {
      "index": 151,
      "start_time": 656200.0,
      "end_time": 659320.0,
      "text": "First of all, it has a great affect on global weather."
    },
    {
      "index": 152,
      "start_time": 659320.0,
      "end_time": 664440.0,
      "text": "We have an ocean that used to be covered with a solid surface that is now depleting."
    },
    {
      "index": 153,
      "start_time": 664500.0,
      "end_time": 667880.0,
      "text": "This affects the position of the jet stream, which now extends"
    },
    {
      "index": 154,
      "start_time": 667880.0,
      "end_time": 669920.0,
      "text": "further north and further south."
    },
    {
      "index": 155,
      "start_time": 669920.0,
      "end_time": 675120.0,
      "text": "Causing blocking patterns to form which increase periods of extreme heat and extreme cold."
    },
    {
      "index": 156,
      "start_time": 675700.0,
      "end_time": 679140.0,
      "text": "It also affects storm tracks, like super storm sand."
    },
    {
      "index": 157,
      "start_time": 679140.0,
      "end_time": 684660.0,
      "text": "The arctic has massive stores of methane in the permafrost and on the arctic seabed."
    },
    {
      "index": 158,
      "start_time": 685320.0,
      "end_time": 688960.0,
      "text": "As we lose the sea ice we have more heat going into the ocean,"
    },
    {
      "index": 159,
      "start_time": 689400.0,
      "end_time": 695700.0,
      "text": "that heat will be transported, causing more permafrost thawing, and destabilization of the seabed."
    },
    {
      "index": 160,
      "start_time": 696080.0,
      "end_time": 700320.0,
      "text": "These processes will increase the overall release of this methane"
    },
    {
      "index": 161,
      "start_time": 700320.0,
      "end_time": 706700.0,
      "text": "which will ultimately contribute to the enhancement of the greenhouse effect and cause a spike in temperature."
    },
    {
      "index": 162,
      "start_time": 707380.0,
      "end_time": 713000.0,
      "text": "The effects of the polar icecaps melting  will also have a significant affect on the chemistry of the ocean,"
    },
    {
      "index": 163,
      "start_time": 713000.0,
      "end_time": 719280.0,
      "text": "more specifically, the composition of the water and the effects it has on living animals."
    },
    {
      "index": 164,
      "start_time": 719680.0,
      "end_time": 727140.0,
      "text": "In the past 20 years, overall land and ocean temperature averages has risen by 1.5 degrees Fahrenheit."
    },
    {
      "index": 165,
      "start_time": 727960.0,
      "end_time": 731380.0,
      "text": "Animals most at risk are those who live in the arctic, especially polar bears,"
    },
    {
      "index": 166,
      "start_time": 732080.0,
      "end_time": 735100.0,
      "text": "since a lot of the ice that they live on has melted."
    },
    {
      "index": 167,
      "start_time": 735100.0,
      "end_time": 740960.0,
      "text": "They face horrid challenges, some of them having to swim for hundreds of miles in hopeless attepmts to find solid ice."
    },
    {
      "index": 168,
      "start_time": 740960.0,
      "end_time": 744260.0,
      "text": "Many are unsuccessful in drowns from exhaustion."
    },
    {
      "index": 169,
      "start_time": 744260.0,
      "end_time": 749520.0,
      "text": "It is probably a process that will happen too quickly for the polar bears to be able to adjust."
    },
    {
      "index": 170,
      "start_time": 749980.0,
      "end_time": 752540.0,
      "text": "Ergo, we are causing their extinction."
    },
    {
      "index": 171,
      "start_time": 753100.0,
      "end_time": 755940.0,
      "text": "We chose to research global warming because we thought it"
    },
    {
      "index": 172,
      "start_time": 756000.0,
      "end_time": 760300.0,
      "text": "was interesting to learn about the effects we as humans have on the planet"
    },
    {
      "index": 173,
      "start_time": 760480.0,
      "end_time": 765540.0,
      "text": "and we can perhaps learn to control our increasing need for energy and"
    },
    {
      "index": 174,
      "start_time": 765540.0,
      "end_time": 770140.0,
      "text": "possibly shift our use of fossil fuels to more sustainable sources"
    },
    {
      "index": 175,
      "start_time": 770140.0,
      "end_time": 773840.0,
      "text": "of energy in order to negate global warming."
    },
    {
      "index": 176,
      "start_time": 773840.0,
      "end_time": 780800.0,
      "text": "It is however becoming ever clearer that global warming is changing the planet at an ever increasing pace."
    },
    {
      "index": 177,
      "start_time": 780800.0,
      "end_time": 786360.0,
      "text": "And if we ignore the causes, it will be a very different planet that our decedents will inherent."
    }
  ]
}