{
  "video_id": "yuqlfM-MX7g",
  "title": "How To Deal With Roundabouts Driving Lesson: Easy To Understand UK Roundabouts",
  "es": 0,
  "json": [
    {
      "index": 1,
      "start_time": 17128.0,
      "end_time": 19128.0,
      "text": "Hello everyone I&#39;m Chris."
    },
    {
      "index": 2,
      "start_time": 19500.0,
      "end_time": 21500.0,
      "text": "In this video we&#39;re going to have a"
    },
    {
      "index": 3,
      "start_time": 21500.0,
      "end_time": 23500.0,
      "text": "look at roundabouts, from how to approach them"
    },
    {
      "index": 4,
      "start_time": 23835.0,
      "end_time": 25835.0,
      "text": "to positioning and when to go."
    },
    {
      "index": 5,
      "start_time": 26687.0,
      "end_time": 28687.0,
      "text": "If you often hesitate at a roundabout"
    },
    {
      "index": 6,
      "start_time": 28687.0,
      "end_time": 30687.0,
      "text": "then stick around as we&#39;ll show you when"
    },
    {
      "index": 7,
      "start_time": 30740.0,
      "end_time": 32739.0,
      "text": "to go and what to look for."
    },
    {
      "index": 8,
      "start_time": 34960.0,
      "end_time": 37540.0,
      "text": "We&#39;re first going to have a look at road positioning"
    },
    {
      "index": 9,
      "start_time": 37540.0,
      "end_time": 39540.0,
      "text": "and how to approach a roundabout"
    },
    {
      "index": 10,
      "start_time": 44292.0,
      "end_time": 46292.0,
      "text": "At this first roundabout"
    },
    {
      "index": 11,
      "start_time": 46292.0,
      "end_time": 48292.0,
      "text": "we will be turning left"
    },
    {
      "index": 12,
      "start_time": 48292.0,
      "end_time": 49792.0,
      "text": "it&#39;s the first exit."
    },
    {
      "index": 13,
      "start_time": 50292.0,
      "end_time": 52292.0,
      "text": "We see the sign for it coming up."
    },
    {
      "index": 14,
      "start_time": 52292.0,
      "end_time": 54292.0,
      "text": "We have to give way to the right."
    },
    {
      "index": 15,
      "start_time": 54292.0,
      "end_time": 56312.0,
      "text": "We&#39;re checking our mirrors to the left."
    },
    {
      "index": 16,
      "start_time": 56940.0,
      "end_time": 58440.0,
      "text": "We signal left, looks all clear,"
    },
    {
      "index": 17,
      "start_time": 58460.0,
      "end_time": 60460.0,
      "text": "going down to 2nd gear and"
    },
    {
      "index": 18,
      "start_time": 60520.0,
      "end_time": 62520.0,
      "text": "keeping in the left hand lane,"
    },
    {
      "index": 19,
      "start_time": 62520.0,
      "end_time": 64520.0,
      "text": "checking mirrors again and keeping the signal on."
    },
    {
      "index": 20,
      "start_time": 64540.00000000001,
      "end_time": 66540.0,
      "text": "Always signal to exit."
    },
    {
      "index": 21,
      "start_time": 68340.0,
      "end_time": 70340.0,
      "text": "At the next roundabout we will turn left and it&#39;s"
    },
    {
      "index": 22,
      "start_time": 70360.0,
      "end_time": 72360.0,
      "text": "the 2nd exit."
    },
    {
      "index": 23,
      "start_time": 73644.0,
      "end_time": 75644.0,
      "text": "You can see on this sign"
    },
    {
      "index": 24,
      "start_time": 75644.0,
      "end_time": 77644.0,
      "text": "that we are coming up from the bottom"
    },
    {
      "index": 25,
      "start_time": 77644.0,
      "end_time": 79644.0,
      "text": "and we need the 2nd exit."
    },
    {
      "index": 26,
      "start_time": 80480.0,
      "end_time": 82480.0,
      "text": "We won&#39;t signal left"
    },
    {
      "index": 27,
      "start_time": 82480.0,
      "end_time": 84480.0,
      "text": "on approach"
    },
    {
      "index": 28,
      "start_time": 84587.0,
      "end_time": 86587.0,
      "text": "or other road users might think that we want"
    },
    {
      "index": 29,
      "start_time": 86587.0,
      "end_time": 88587.0,
      "text": "the 1st exit"
    },
    {
      "index": 30,
      "start_time": 88587.0,
      "end_time": 90587.0,
      "text": "but we will keep in the left hand lane."
    },
    {
      "index": 31,
      "start_time": 97980.0,
      "end_time": 99980.0,
      "text": "As we&#39;re passing"
    },
    {
      "index": 32,
      "start_time": 100000.0,
      "end_time": 102000.0,
      "text": "the 1st exit we will check our mirrors"
    },
    {
      "index": 33,
      "start_time": 102140.0,
      "end_time": 104140.0,
      "text": "and we&#39;ll signal left to exit."
    },
    {
      "index": 34,
      "start_time": 107320.0,
      "end_time": 109320.0,
      "text": "We&#39;re now going to have a look at different variations of"
    },
    {
      "index": 35,
      "start_time": 109320.0,
      "end_time": 111320.0,
      "text": "following the road ahead at a roundabout."
    },
    {
      "index": 36,
      "start_time": 115898.0,
      "end_time": 120538.0,
      "text": "At the next roundabout we will follow the road ahead, it&#39;s the 2nd exit."
    },
    {
      "index": 37,
      "start_time": 120550.0,
      "end_time": 122550.0,
      "text": "Just like at a crossroads, if you&#39;re following the road ahead"
    },
    {
      "index": 38,
      "start_time": 122700.0,
      "end_time": 125874.0,
      "text": "you&#39;d be in the left hand lane unless road markings or signs tell you otherwise."
    },
    {
      "index": 39,
      "start_time": 125874.0,
      "end_time": 127874.0,
      "text": "Again we give-way to the right"
    },
    {
      "index": 40,
      "start_time": 127874.0,
      "end_time": 129874.0,
      "text": "and now it&#39;s very important"
    },
    {
      "index": 41,
      "start_time": 129874.0,
      "end_time": 131874.0,
      "text": "to keep in the left-hand lane"
    },
    {
      "index": 42,
      "start_time": 131874.0,
      "end_time": 133874.0,
      "text": "and I really mean"
    },
    {
      "index": 43,
      "start_time": 133874.0,
      "end_time": 134954.0,
      "text": "keep left."
    },
    {
      "index": 44,
      "start_time": 135120.0,
      "end_time": 137120.0,
      "text": "Now we check mirrors to the left"
    },
    {
      "index": 45,
      "start_time": 137140.0,
      "end_time": 139140.0,
      "text": "and signal left"
    },
    {
      "index": 46,
      "start_time": 139180.0,
      "end_time": 141180.0,
      "text": "It was very important to keep in the left hand lane"
    },
    {
      "index": 47,
      "start_time": 141240.0,
      "end_time": 143240.0,
      "text": "as we might of had someone else next"
    },
    {
      "index": 48,
      "start_time": 143260.0,
      "end_time": 145260.0,
      "text": "to us turning right."
    },
    {
      "index": 49,
      "start_time": 148200.0,
      "end_time": 150393.0,
      "text": "At the next roundabout"
    },
    {
      "index": 50,
      "start_time": 150394.0,
      "end_time": 152394.0,
      "text": "we will follow the road ahead"
    },
    {
      "index": 51,
      "start_time": 152394.0,
      "end_time": 154394.0,
      "text": "it&#39;s the 2nd exit"
    },
    {
      "index": 52,
      "start_time": 154394.0,
      "end_time": 156394.0,
      "text": "Now this roundabout will have 3 lanes."
    },
    {
      "index": 53,
      "start_time": 156394.0,
      "end_time": 158394.0,
      "text": "Again we will keep in the left hand lane"
    },
    {
      "index": 54,
      "start_time": 158440.0,
      "end_time": 160440.0,
      "text": "unless there&#39;s markings or signs telling us"
    },
    {
      "index": 55,
      "start_time": 160440.0,
      "end_time": 162440.0,
      "text": "any different."
    },
    {
      "index": 56,
      "start_time": 162440.0,
      "end_time": 164440.0,
      "text": "The lane in the middle would be used"
    },
    {
      "index": 57,
      "start_time": 164440.0,
      "end_time": 166440.0,
      "text": "for overtaking if there was a big traffic"
    },
    {
      "index": 58,
      "start_time": 166440.0,
      "end_time": 167859.0,
      "text": "jam in the left hand lane."
    },
    {
      "index": 59,
      "start_time": 168700.0,
      "end_time": 170700.0,
      "text": "Giving way to the right."
    },
    {
      "index": 60,
      "start_time": 170700.0,
      "end_time": 172700.0,
      "text": "Looks quite busy, being prepared to stop."
    },
    {
      "index": 61,
      "start_time": 176400.0,
      "end_time": 178887.0,
      "text": "When we join the roundabout"
    },
    {
      "index": 62,
      "start_time": 178887.0,
      "end_time": 180887.0,
      "text": "we need to keep in the left hand lane."
    },
    {
      "index": 63,
      "start_time": 180887.0,
      "end_time": 182887.0,
      "text": "Getting up to 2nd gear now."
    },
    {
      "index": 64,
      "start_time": 182887.0,
      "end_time": 184887.0,
      "text": "checking mirrors and signal to exit."
    },
    {
      "index": 65,
      "start_time": 190247.0,
      "end_time": 192247.0,
      "text": "At this next roundabout"
    },
    {
      "index": 66,
      "start_time": 192247.0,
      "end_time": 194247.0,
      "text": "we will follow the road ahead."
    },
    {
      "index": 67,
      "start_time": 194920.0,
      "end_time": 196920.0,
      "text": "This ones a bit different"
    },
    {
      "index": 68,
      "start_time": 197500.0,
      "end_time": 199500.0,
      "text": "as it will go into 3 lanes and the sign"
    },
    {
      "index": 69,
      "start_time": 199500.0,
      "end_time": 201500.0,
      "text": "on the left and the road markings"
    },
    {
      "index": 70,
      "start_time": 201500.0,
      "end_time": 203000.0,
      "text": "will tell us that"
    },
    {
      "index": 71,
      "start_time": 203140.0,
      "end_time": 204839.0,
      "text": "we will need the middle lane as"
    },
    {
      "index": 72,
      "start_time": 204880.0,
      "end_time": 206880.0,
      "text": "the left-hand lane is for turning"
    },
    {
      "index": 73,
      "start_time": 206900.0,
      "end_time": 208180.0,
      "text": "left only."
    },
    {
      "index": 74,
      "start_time": 208260.0,
      "end_time": 210260.0,
      "text": "Now I&#39;ve got this white van blocking my view"
    },
    {
      "index": 75,
      "start_time": 210300.0,
      "end_time": 212300.0,
      "text": "so I&#39;m going to creep forward slowly"
    },
    {
      "index": 76,
      "start_time": 212340.0,
      "end_time": 214340.0,
      "text": "and try and get a better view."
    },
    {
      "index": 77,
      "start_time": 214400.0,
      "end_time": 216400.0,
      "text": "Now he&#39;s gone and I&#39;ve got a good view,"
    },
    {
      "index": 78,
      "start_time": 216440.0,
      "end_time": 217940.0,
      "text": "it&#39;s clear"
    },
    {
      "index": 79,
      "start_time": 217980.0,
      "end_time": 219000.0,
      "text": "and I&#39;m keeping to the left now."
    },
    {
      "index": 80,
      "start_time": 219000.0,
      "end_time": 221000.0,
      "text": "I&#39;m watching these vehicles on the left"
    },
    {
      "index": 81,
      "start_time": 221000.0,
      "end_time": 223540.0,
      "text": "in case they pull out, checking my mirrors, signal left to exit."
    },
    {
      "index": 82,
      "start_time": 223560.0,
      "end_time": 225560.0,
      "text": "Staying in the left hand lane."
    },
    {
      "index": 83,
      "start_time": 228903.0,
      "end_time": 230903.0,
      "text": "We&#39;re now going to have a look"
    },
    {
      "index": 84,
      "start_time": 230903.0,
      "end_time": 232903.0,
      "text": "at turning right at a roundabout."
    },
    {
      "index": 85,
      "start_time": 235421.0,
      "end_time": 237421.0,
      "text": "At this next roundabout I am turning right"
    },
    {
      "index": 86,
      "start_time": 237421.0,
      "end_time": 239421.0,
      "text": "4th exit."
    },
    {
      "index": 87,
      "start_time": 239421.0,
      "end_time": 241421.0,
      "text": "Because it&#39;s to the right"
    },
    {
      "index": 88,
      "start_time": 241421.0,
      "end_time": 243421.0,
      "text": "half of the roundabout, I&#39;ve had to"
    },
    {
      "index": 89,
      "start_time": 244601.0,
      "end_time": 246601.0,
      "text": "change into the right-hand lane"
    },
    {
      "index": 90,
      "start_time": 246601.0,
      "end_time": 248601.0,
      "text": "I&#39;ve checked my mirrors and signalling right."
    },
    {
      "index": 91,
      "start_time": 249510.0,
      "end_time": 251510.0,
      "text": "I can see my opportunity"
    },
    {
      "index": 92,
      "start_time": 251880.0,
      "end_time": 253880.0,
      "text": "keeping in the right-hand lane."
    },
    {
      "index": 93,
      "start_time": 253720.0,
      "end_time": 255720.0,
      "text": "I&#39;m up to 2nd gear now."
    },
    {
      "index": 94,
      "start_time": 257620.0,
      "end_time": 259620.0,
      "text": "Still got my signal on to the right."
    },
    {
      "index": 95,
      "start_time": 261600.00000000003,
      "end_time": 263600.0,
      "text": "I&#39;m just counting the exits as I go round."
    },
    {
      "index": 96,
      "start_time": 263740.0,
      "end_time": 265240.0,
      "text": "This will be the 2nd exit"
    },
    {
      "index": 97,
      "start_time": 265420.0,
      "end_time": 267275.0,
      "text": "As I&#39;m passing the 3rd,"
    },
    {
      "index": 98,
      "start_time": 267275.0,
      "end_time": 269275.0,
      "text": "I&#39;m checking my mirrors to the left, signal left"
    },
    {
      "index": 99,
      "start_time": 269420.0,
      "end_time": 271420.0,
      "text": "and I&#39;m moving over to exit."
    },
    {
      "index": 100,
      "start_time": 276720.0,
      "end_time": 278720.0,
      "text": "Taking the 2nd exit at a roundabout"
    },
    {
      "index": 101,
      "start_time": 278720.0,
      "end_time": 280720.0,
      "text": "doesn&#39;t always mean that"
    },
    {
      "index": 102,
      "start_time": 280720.0,
      "end_time": 282720.0,
      "text": "you&#39;ll be following the road ahead."
    },
    {
      "index": 103,
      "start_time": 282720.0,
      "end_time": 284720.0,
      "text": "This next roundabout"
    },
    {
      "index": 104,
      "start_time": 284720.0,
      "end_time": 286720.0,
      "text": "is a good example"
    },
    {
      "index": 105,
      "start_time": 286720.0,
      "end_time": 288720.0,
      "text": "where the 2nd exit"
    },
    {
      "index": 106,
      "start_time": 288720.0,
      "end_time": 290720.0,
      "text": "is actually to the right."
    },
    {
      "index": 107,
      "start_time": 290720.0,
      "end_time": 292720.0,
      "text": "As you can see by the sign here."
    },
    {
      "index": 108,
      "start_time": 292720.0,
      "end_time": 294720.0,
      "text": "We&#39;ll be going towards Shirley."
    },
    {
      "index": 109,
      "start_time": 294720.0,
      "end_time": 296720.0,
      "text": "Because the exit is"
    },
    {
      "index": 110,
      "start_time": 296720.0,
      "end_time": 298720.0,
      "text": "slightly to the right of the roundabout"
    },
    {
      "index": 111,
      "start_time": 298720.0,
      "end_time": 300720.0,
      "text": "we will check our mirrors to the right"
    },
    {
      "index": 112,
      "start_time": 300720.0,
      "end_time": 302720.0,
      "text": "signal right and keep in"
    },
    {
      "index": 113,
      "start_time": 302720.0,
      "end_time": 304720.0,
      "text": "the right-hand lane."
    },
    {
      "index": 114,
      "start_time": 304720.0,
      "end_time": 306720.0,
      "text": "As soon as we&#39;re passing the 1st exit"
    },
    {
      "index": 115,
      "start_time": 306860.0,
      "end_time": 308860.0,
      "text": "check mirrors, signal and exit."
    },
    {
      "index": 116,
      "start_time": 312600.0,
      "end_time": 314600.0,
      "text": "At this next roundabout"
    },
    {
      "index": 117,
      "start_time": 315380.0,
      "end_time": 317380.0,
      "text": "We need to turn right"
    },
    {
      "index": 118,
      "start_time": 317380.0,
      "end_time": 319380.0,
      "text": "2nd exit."
    },
    {
      "index": 119,
      "start_time": 319380.0,
      "end_time": 321380.0,
      "text": "Our exit that we need is slightly to the"
    },
    {
      "index": 120,
      "start_time": 321380.0,
      "end_time": 323380.0,
      "text": "right of the roundabout"
    },
    {
      "index": 121,
      "start_time": 323380.0,
      "end_time": 325380.0,
      "text": "and that&#39;s why we need the"
    },
    {
      "index": 122,
      "start_time": 325380.0,
      "end_time": 327380.0,
      "text": "right-hand lane and signal right."
    },
    {
      "index": 123,
      "start_time": 327380.0,
      "end_time": 329380.0,
      "text": "We need to be careful not to stop on the crossing."
    },
    {
      "index": 124,
      "start_time": 330282.0,
      "end_time": 332282.0,
      "text": "Not only do we not stop on it"
    },
    {
      "index": 125,
      "start_time": 332282.0,
      "end_time": 334282.0,
      "text": "but we need to make sure it&#39;s clear"
    },
    {
      "index": 126,
      "start_time": 334282.0,
      "end_time": 336282.0,
      "text": "before going."
    },
    {
      "index": 127,
      "start_time": 336282.0,
      "end_time": 338282.0,
      "text": "We don&#39;t want to get distracted"
    },
    {
      "index": 128,
      "start_time": 338282.0,
      "end_time": 340282.0,
      "text": "just by the roundabout."
    },
    {
      "index": 129,
      "start_time": 340282.0,
      "end_time": 342282.0,
      "text": "The crossing looks clear and so does"
    },
    {
      "index": 130,
      "start_time": 342282.0,
      "end_time": 344282.0,
      "text": "the roundabout."
    },
    {
      "index": 131,
      "start_time": 344282.0,
      "end_time": 346282.0,
      "text": "We&#39;re keeping in the right-hand"
    },
    {
      "index": 132,
      "start_time": 346282.0,
      "end_time": 348282.0,
      "text": "lane and as soon as we&#39;re passing the 1st exit,"
    },
    {
      "index": 133,
      "start_time": 348340.0,
      "end_time": 350340.0,
      "text": "check our mirrors to the left, signal left and then exit."
    },
    {
      "index": 134,
      "start_time": 350340.0,
      "end_time": 352340.0,
      "text": "Looking out for the next zebra crossing."
    },
    {
      "index": 135,
      "start_time": 357740.0,
      "end_time": 359740.0,
      "text": "You can also use roundabouts as a way of turning"
    },
    {
      "index": 136,
      "start_time": 359740.0,
      "end_time": 361740.0,
      "text": "around."
    },
    {
      "index": 137,
      "start_time": 361740.0,
      "end_time": 363740.0,
      "text": "At the next roundabout we will turn right and it&#39;s the"
    },
    {
      "index": 138,
      "start_time": 363740.0,
      "end_time": 365740.0,
      "text": "4th exit."
    },
    {
      "index": 139,
      "start_time": 365740.0,
      "end_time": 367740.0,
      "text": "So we&#39;ve changed lanes"
    },
    {
      "index": 140,
      "start_time": 369300.0,
      "end_time": 371300.0,
      "text": "we need to keep in the furthest right"
    },
    {
      "index": 141,
      "start_time": 371300.0,
      "end_time": 373300.0,
      "text": "hand lane."
    },
    {
      "index": 142,
      "start_time": 392187.0,
      "end_time": 394187.0,
      "text": "Still keeping in the right-hand lane."
    },
    {
      "index": 143,
      "start_time": 394800.0,
      "end_time": 396800.0,
      "text": "As soon as we&#39;re passing the 3rd exit,"
    },
    {
      "index": 144,
      "start_time": 396800.0,
      "end_time": 398800.0,
      "text": "check mirrors to the left, signal and then"
    },
    {
      "index": 145,
      "start_time": 398800.0,
      "end_time": 400800.0,
      "text": "exit."
    },
    {
      "index": 146,
      "start_time": 404760.0,
      "end_time": 406760.0,
      "text": "This next roundabout is a little more complicated"
    },
    {
      "index": 147,
      "start_time": 406760.0,
      "end_time": 408760.0,
      "text": "as it&#39;s partly controlled by traffic lights."
    },
    {
      "index": 148,
      "start_time": 408760.0,
      "end_time": 410760.0,
      "text": "There&#39;s also multiple lanes"
    },
    {
      "index": 149,
      "start_time": 413440.0,
      "end_time": 415440.0,
      "text": "We have to give-way to the right here as usual."
    },
    {
      "index": 150,
      "start_time": 417340.0,
      "end_time": 419340.0,
      "text": "Now we&#39;re following the road markings and"
    },
    {
      "index": 151,
      "start_time": 419340.0,
      "end_time": 421340.0,
      "text": "signs to the A14 east."
    },
    {
      "index": 152,
      "start_time": 421340.0,
      "end_time": 423340.0,
      "text": "We could see it written in the road there."
    },
    {
      "index": 153,
      "start_time": 423960.0,
      "end_time": 425960.0,
      "text": "This part is now controlled by traffic lights."
    },
    {
      "index": 154,
      "start_time": 427415.0,
      "end_time": 429415.0,
      "text": "It&#39;s green so we&#39;ve got priority."
    },
    {
      "index": 155,
      "start_time": 430779.0,
      "end_time": 432779.0,
      "text": "Keeping in lane towards the A14 east."
    },
    {
      "index": 156,
      "start_time": 461618.0,
      "end_time": 463618.0,
      "text": "Now we&#39;re taking the next exit towards the A14 east."
    },
    {
      "index": 157,
      "start_time": 470470.0,
      "end_time": 472470.0,
      "text": "We go from one extreme to another as we now"
    },
    {
      "index": 158,
      "start_time": 472470.0,
      "end_time": 474470.0,
      "text": "have a look at mini-roundabouts."
    },
    {
      "index": 159,
      "start_time": 474470.0,
      "end_time": 476470.0,
      "text": "You could say that mini-roundabouts"
    },
    {
      "index": 160,
      "start_time": 476470.0,
      "end_time": 478470.0,
      "text": "are friendlier than some of the larger ones."
    },
    {
      "index": 161,
      "start_time": 478470.0,
      "end_time": 480470.0,
      "text": "Same rules,"
    },
    {
      "index": 162,
      "start_time": 480470.0,
      "end_time": 482470.0,
      "text": "still give-way to the right,"
    },
    {
      "index": 163,
      "start_time": 482470.0,
      "end_time": 484470.0,
      "text": "signal the same, you don&#39;t have to"
    },
    {
      "index": 164,
      "start_time": 484624.0,
      "end_time": 486624.0,
      "text": "signal to exit if you don&#39;t have time."
    },
    {
      "index": 165,
      "start_time": 486624.0,
      "end_time": 488624.0,
      "text": "At the next mini-roundabout"
    },
    {
      "index": 166,
      "start_time": 488624.0,
      "end_time": 490624.0,
      "text": "we will follow the road ahead"
    },
    {
      "index": 167,
      "start_time": 490624.0,
      "end_time": 492624.0,
      "text": "give-way to the right, but it&#39;s well"
    },
    {
      "index": 168,
      "start_time": 492624.0,
      "end_time": 494624.0,
      "text": "worth checking to the left as well to"
    },
    {
      "index": 169,
      "start_time": 494624.0,
      "end_time": 496624.0,
      "text": "make sure that no one is pulling out when they"
    },
    {
      "index": 170,
      "start_time": 496624.0,
      "end_time": 498624.0,
      "text": "shouldn&#39;t."
    },
    {
      "index": 171,
      "start_time": 498700.0,
      "end_time": 500700.0,
      "text": "See another sign for a mini-roundabout."
    },
    {
      "index": 172,
      "start_time": 500700.0,
      "end_time": 502700.0,
      "text": "Again we&#39;re following the road ahead."
    },
    {
      "index": 173,
      "start_time": 508420.0,
      "end_time": 510420.0,
      "text": "At the next mini-roundabout, we will"
    },
    {
      "index": 174,
      "start_time": 510420.0,
      "end_time": 512420.0,
      "text": "turn right."
    },
    {
      "index": 175,
      "start_time": 512774.0,
      "end_time": 514774.0,
      "text": "This is a good example of a mini-roundabout"
    },
    {
      "index": 176,
      "start_time": 514774.0,
      "end_time": 516774.0,
      "text": "that is impossible to go round."
    },
    {
      "index": 177,
      "start_time": 516774.0,
      "end_time": 518774.0,
      "text": "Especially if there&#39;s a parked car in the way."
    },
    {
      "index": 178,
      "start_time": 518774.0,
      "end_time": 520774.0,
      "text": "But, we&#39;ll do our best."
    },
    {
      "index": 179,
      "start_time": 520774.0,
      "end_time": 522774.0,
      "text": "Don&#39;t be afraid to drive on it if you need to."
    },
    {
      "index": 180,
      "start_time": 524300.0,
      "end_time": 526300.0,
      "text": "Here we have another example of a mini-roundabout"
    },
    {
      "index": 181,
      "start_time": 526300.0,
      "end_time": 528300.0,
      "text": "that is again impossible to drive around."
    },
    {
      "index": 182,
      "start_time": 528300.0,
      "end_time": 530300.0,
      "text": "Parked cars in the way."
    },
    {
      "index": 183,
      "start_time": 530300.0,
      "end_time": 532300.0,
      "text": "We&#39;re turning right."
    },
    {
      "index": 184,
      "start_time": 534684.0,
      "end_time": 536684.0,
      "text": "Drive on it a bit, especially as this road is so tight."
    },
    {
      "index": 185,
      "start_time": 537924.0,
      "end_time": 540944.0,
      "text": "Again, plan ahead as you don&#39;t want to get stuck behind a parked car."
    },
    {
      "index": 186,
      "start_time": 542880.0,
      "end_time": 544880.0,
      "text": "Don&#39;t be afraid to drive on a mini-roundabout if you need to,"
    },
    {
      "index": 187,
      "start_time": 545830.0,
      "end_time": 547830.0,
      "text": "as long as you try your best to go round it."
    },
    {
      "index": 188,
      "start_time": 549920.0,
      "end_time": 551920.0,
      "text": "Now we have 2 mini-roundabouts coming up."
    },
    {
      "index": 189,
      "start_time": 552502.0,
      "end_time": 554502.0,
      "text": "We will follow the road ahead at both of them."
    },
    {
      "index": 190,
      "start_time": 558153.0,
      "end_time": 560153.0,
      "text": "Treat them as 2 separate individual roundabouts."
    },
    {
      "index": 191,
      "start_time": 560153.0,
      "end_time": 562153.0,
      "text": "Give-way to the right."
    },
    {
      "index": 192,
      "start_time": 563600.0,
      "end_time": 565600.0,
      "text": "Again, follow the road ahead and it&#39;s all clear"
    },
    {
      "index": 193,
      "start_time": 565600.0,
      "end_time": 567600.0,
      "text": "to the right,"
    },
    {
      "index": 194,
      "start_time": 567640.0,
      "end_time": 569640.0,
      "text": "which is basically cars opposite."
    },
    {
      "index": 195,
      "start_time": 576240.0,
      "end_time": 578240.0,
      "text": "We&#39;re approaching those 2 mini-roundabouts again."
    },
    {
      "index": 196,
      "start_time": 579272.0,
      "end_time": 581272.0,
      "text": "This time we will turn right at the first one and"
    },
    {
      "index": 197,
      "start_time": 581272.0,
      "end_time": 583272.0,
      "text": "left at the 2nd one."
    },
    {
      "index": 198,
      "start_time": 583272.0,
      "end_time": 585272.0,
      "text": "We&#39;re checking mirrors to the right"
    },
    {
      "index": 199,
      "start_time": 585272.0,
      "end_time": 587272.0,
      "text": "signal right"
    },
    {
      "index": 200,
      "start_time": 587272.0,
      "end_time": 589272.0,
      "text": "it&#39;s all clear to the right."
    },
    {
      "index": 201,
      "start_time": 589272.0,
      "end_time": 591272.0,
      "text": "Now we&#39;re turning left,"
    },
    {
      "index": 202,
      "start_time": 591272.0,
      "end_time": 593272.0,
      "text": "check mirrors to the left and signal left."
    },
    {
      "index": 203,
      "start_time": 593272.0,
      "end_time": 595272.0,
      "text": "Giving way to the right and it&#39;s all clear."
    },
    {
      "index": 204,
      "start_time": 598620.0,
      "end_time": 600620.0,
      "text": "This next mini-roundabout is fairly busy."
    },
    {
      "index": 205,
      "start_time": 602654.0,
      "end_time": 604654.0,
      "text": "We know that we have to give-way to the right"
    },
    {
      "index": 206,
      "start_time": 605440.0,
      "end_time": 607440.0,
      "text": "We&#39;re turning left."
    },
    {
      "index": 207,
      "start_time": 610600.0,
      "end_time": 612600.0,
      "text": "If a vehicle from the left, turns right"
    },
    {
      "index": 208,
      "start_time": 612120.0,
      "end_time": 614120.0,
      "text": "to where we just come from like this van"
    },
    {
      "index": 209,
      "start_time": 614555.0,
      "end_time": 616555.0,
      "text": "they will block the vehicles on the right"
    },
    {
      "index": 210,
      "start_time": 616555.0,
      "end_time": 618555.0,
      "text": "and give us a chance to go."
    },
    {
      "index": 211,
      "start_time": 624840.0,
      "end_time": 626840.0,
      "text": "The next part of this video"
    },
    {
      "index": 212,
      "start_time": 630157.0,
      "end_time": 632157.0,
      "text": "is all about when to go onto a roundabout."
    },
    {
      "index": 213,
      "start_time": 632369.0,
      "end_time": 634369.0,
      "text": "You&#39;ll have to use your anticipation skills to judge when it&#39;s safe to go."
    },
    {
      "index": 214,
      "start_time": 634740.0,
      "end_time": 636740.0,
      "text": "Especially on busy roundabouts."
    },
    {
      "index": 215,
      "start_time": 636880.0,
      "end_time": 638880.0,
      "text": "I&#39;m going to show you clues to look out for"
    },
    {
      "index": 216,
      "start_time": 639187.0,
      "end_time": 641187.0,
      "text": "so you won&#39;t miss opportunities."
    },
    {
      "index": 217,
      "start_time": 648400.0,
      "end_time": 650400.0,
      "text": "We obviously have to give-way to the right"
    },
    {
      "index": 218,
      "start_time": 650632.0,
      "end_time": 652632.0,
      "text": "but what we&#39;re looking for is"
    },
    {
      "index": 219,
      "start_time": 652632.0,
      "end_time": 654632.0,
      "text": "a vehicle that is going to exit the roundabout"
    },
    {
      "index": 220,
      "start_time": 654632.0,
      "end_time": 656632.0,
      "text": "to where we just come from."
    },
    {
      "index": 221,
      "start_time": 657400.0,
      "end_time": 659400.0,
      "text": "See these 2 cars exiting"
    },
    {
      "index": 222,
      "start_time": 659400.0,
      "end_time": 661400.0,
      "text": "which gives us a chance to go."
    },
    {
      "index": 223,
      "start_time": 663746.0,
      "end_time": 665746.0,
      "text": "But how do we know"
    },
    {
      "index": 224,
      "start_time": 665746.0,
      "end_time": 667746.0,
      "text": "when a vehicle is going to exit"
    },
    {
      "index": 225,
      "start_time": 667746.0,
      "end_time": 669746.0,
      "text": "the roundabout and give us a chance to"
    },
    {
      "index": 226,
      "start_time": 669746.0,
      "end_time": 671746.0,
      "text": "get on?"
    },
    {
      "index": 227,
      "start_time": 672000.0,
      "end_time": 674000.0,
      "text": "We don&#39;t rely on other vehicles signals"
    },
    {
      "index": 228,
      "start_time": 674000.0,
      "end_time": 676000.0,
      "text": "as they don&#39;t signal correctly or at all like that white"
    },
    {
      "index": 229,
      "start_time": 676000.0,
      "end_time": 678000.0,
      "text": "van."
    },
    {
      "index": 230,
      "start_time": 680200.0,
      "end_time": 682200.0,
      "text": "As we can&#39;t rely on their signals, we need to look out for other clues."
    },
    {
      "index": 231,
      "start_time": 682240.0,
      "end_time": 684240.0,
      "text": "For example where they&#39;re steering, their positioning and angle."
    },
    {
      "index": 232,
      "start_time": 684479.0,
      "end_time": 686479.0,
      "text": "Let&#39;s have a look at some more examples."
    },
    {
      "index": 233,
      "start_time": 686687.0,
      "end_time": 688687.0,
      "text": "This next opportunity is a little bit easier."
    },
    {
      "index": 234,
      "start_time": 688687.0,
      "end_time": 690687.0,
      "text": "I&#39;m looking at the speed"
    },
    {
      "index": 235,
      "start_time": 690687.0,
      "end_time": 692687.0,
      "text": "of these cars"
    },
    {
      "index": 236,
      "start_time": 692687.0,
      "end_time": 694687.0,
      "text": "this blue car is going quite fast,"
    },
    {
      "index": 237,
      "start_time": 694687.0,
      "end_time": 696687.0,
      "text": "I know he&#39;s not going to bother me."
    },
    {
      "index": 238,
      "start_time": 699310.0,
      "end_time": 701310.0,
      "text": "Normally if the other car is going quite fast"
    },
    {
      "index": 239,
      "start_time": 701310.0,
      "end_time": 703310.0,
      "text": "they&#39;re probably zooming off to exit."
    },
    {
      "index": 240,
      "start_time": 703310.0,
      "end_time": 705310.0,
      "text": "With this next opportunity"
    },
    {
      "index": 241,
      "start_time": 705310.0,
      "end_time": 707310.0,
      "text": "I&#39;m going to slow the video"
    },
    {
      "index": 242,
      "start_time": 707310.0,
      "end_time": 709310.0,
      "text": "down to show you how you can look"
    },
    {
      "index": 243,
      "start_time": 709310.0,
      "end_time": 711310.0,
      "text": "at other vehicles postion"
    },
    {
      "index": 244,
      "start_time": 711310.0,
      "end_time": 713310.0,
      "text": "and angle to give you a good clue"
    },
    {
      "index": 245,
      "start_time": 713310.0,
      "end_time": 715310.0,
      "text": "that they&#39;re coming off."
    },
    {
      "index": 246,
      "start_time": 716302.0,
      "end_time": 718302.0,
      "text": "With this red car, you can see how their front wheels are dead straight"
    },
    {
      "index": 247,
      "start_time": 718302.0,
      "end_time": 720302.0,
      "text": "there&#39;s no way that this car is"
    },
    {
      "index": 248,
      "start_time": 721880.0,
      "end_time": 723880.0,
      "text": "coming round and bother me, so this gives me"
    },
    {
      "index": 249,
      "start_time": 724327.0,
      "end_time": 726327.0,
      "text": "a chance to get on with no hesitation."
    },
    {
      "index": 250,
      "start_time": 728516.0,
      "end_time": 730516.0,
      "text": "Lets see if you know when to go"
    },
    {
      "index": 251,
      "start_time": 730516.0,
      "end_time": 732516.0,
      "text": "on this next roundabout."
    },
    {
      "index": 252,
      "start_time": 734000.0,
      "end_time": 736000.0,
      "text": "Again, we&#39;ll have another bus."
    },
    {
      "index": 253,
      "start_time": 736832.0,
      "end_time": 738832.0,
      "text": "It&#39;s very hard to tell where this bus is"
    },
    {
      "index": 254,
      "start_time": 738832.0,
      "end_time": 740832.0,
      "text": "going."
    },
    {
      "index": 255,
      "start_time": 740832.0,
      "end_time": 742832.0,
      "text": "But as we emerge further we can see that"
    },
    {
      "index": 256,
      "start_time": 742832.0,
      "end_time": 744832.0,
      "text": "he&#39;s going dead straight and not bothering us."
    },
    {
      "index": 257,
      "start_time": 747419.0,
      "end_time": 749419.0,
      "text": "Again I was watching their front wheels"
    },
    {
      "index": 258,
      "start_time": 754460.0,
      "end_time": 756460.0,
      "text": "Let&#39;s slow this next roundabout down."
    },
    {
      "index": 259,
      "start_time": 756460.0,
      "end_time": 758460.0,
      "text": "Would you take this next opportunity?"
    },
    {
      "index": 260,
      "start_time": 760786.0,
      "end_time": 762786.0,
      "text": "Look at their front wheels."
    },
    {
      "index": 261,
      "start_time": 762786.0,
      "end_time": 764786.0,
      "text": "Look where they&#39;re steering."
    },
    {
      "index": 262,
      "start_time": 771620.0,
      "end_time": 773620.0,
      "text": "Whatever you do, don&#39;t rely on other peoples"
    },
    {
      "index": 263,
      "start_time": 773620.0,
      "end_time": 775620.0,
      "text": "signals."
    },
    {
      "index": 264,
      "start_time": 776382.0,
      "end_time": 778382.0,
      "text": "Another roundabout."
    },
    {
      "index": 265,
      "start_time": 778382.0,
      "end_time": 780382.0,
      "text": "And a little bit busier.."
    },
    {
      "index": 266,
      "start_time": 782200.0,
      "end_time": 784200.0,
      "text": "Watch their front wheels..."
    },
    {
      "index": 267,
      "start_time": 784380.0,
      "end_time": 786380.0,
      "text": "Their position and are they speeding up."
    },
    {
      "index": 268,
      "start_time": 788471.0,
      "end_time": 790471.0,
      "text": "Great opportunity there."
    },
    {
      "index": 269,
      "start_time": 791680.0,
      "end_time": 793680.0,
      "text": "Got to be quick, got to be confident"
    },
    {
      "index": 270,
      "start_time": 793860.0,
      "end_time": 795860.0,
      "text": "at fast you can pull away."
    },
    {
      "index": 271,
      "start_time": 795860.0,
      "end_time": 797860.0,
      "text": "Don&#39;t take any dangerous chances."
    },
    {
      "index": 272,
      "start_time": 799000.0,
      "end_time": 801000.0,
      "text": "Plan ahead"
    },
    {
      "index": 273,
      "start_time": 802458.0,
      "end_time": 804458.0,
      "text": "Watch those other drivers, watch their front"
    },
    {
      "index": 274,
      "start_time": 804458.0,
      "end_time": 806458.0,
      "text": "wheels."
    },
    {
      "index": 275,
      "start_time": 806458.0,
      "end_time": 808458.0,
      "text": "Sometimes you get lucky and it&#39;s totally clear."
    },
    {
      "index": 276,
      "start_time": 808458.0,
      "end_time": 810458.0,
      "text": "These are the roundabouts we like."
    },
    {
      "index": 277,
      "start_time": 814980.0,
      "end_time": 816980.0,
      "text": "This next roundabout, there is a car on"
    },
    {
      "index": 278,
      "start_time": 816980.0,
      "end_time": 818980.0,
      "text": "our right,"
    },
    {
      "index": 279,
      "start_time": 818980.0,
      "end_time": 820980.0,
      "text": "but because we have more momentum"
    },
    {
      "index": 280,
      "start_time": 820980.0,
      "end_time": 822980.0,
      "text": "more speed than they do"
    },
    {
      "index": 281,
      "start_time": 822980.0,
      "end_time": 824980.0,
      "text": "we can get on easily"
    },
    {
      "index": 282,
      "start_time": 824980.0,
      "end_time": 826980.0,
      "text": "without bothering them."
    },
    {
      "index": 283,
      "start_time": 826980.0,
      "end_time": 828980.0,
      "text": "Now we have a zebra crossing to watch out for"
    },
    {
      "index": 284,
      "start_time": 828980.0,
      "end_time": 830980.0,
      "text": "as well as a roundabout."
    },
    {
      "index": 285,
      "start_time": 830980.0,
      "end_time": 832980.0,
      "text": "Once the zebra crossing is clear,"
    },
    {
      "index": 286,
      "start_time": 832980.0,
      "end_time": 834980.0,
      "text": "we&#39;re checking the roundabout"
    },
    {
      "index": 287,
      "start_time": 834980.0,
      "end_time": 836980.0,
      "text": "the black car was coming off and gave"
    },
    {
      "index": 288,
      "start_time": 836980.0,
      "end_time": 838980.0,
      "text": "us a great chance to get on."
    },
    {
      "index": 289,
      "start_time": 839260.0,
      "end_time": 841260.0,
      "text": "Let&#39;s have a look at this next roundabout"
    },
    {
      "index": 290,
      "start_time": 841320.0,
      "end_time": 843320.0,
      "text": "for that golden opportunity."
    },
    {
      "index": 291,
      "start_time": 845436.0,
      "end_time": 847436.0,
      "text": "We&#39;re watching this silver car"
    },
    {
      "index": 292,
      "start_time": 847436.0,
      "end_time": 849436.0,
      "text": "that&#39;s coming round the roundabout."
    },
    {
      "index": 293,
      "start_time": 849436.0,
      "end_time": 851436.0,
      "text": "And it&#39;s at this point that we can see"
    },
    {
      "index": 294,
      "start_time": 851436.0,
      "end_time": 853436.0,
      "text": "that their front wheels are straightening up"
    },
    {
      "index": 295,
      "start_time": 853440.0,
      "end_time": 855440.0,
      "text": "and their angle is pointing down where we&#39;ve just come from."
    },
    {
      "index": 296,
      "start_time": 855440.0,
      "end_time": 857440.0,
      "text": "Giving us a great opportunity."
    },
    {
      "index": 297,
      "start_time": 860300.0,
      "end_time": 862300.0,
      "text": "Got to be quick, don&#39;t want to cause other drivers to"
    },
    {
      "index": 298,
      "start_time": 862300.0,
      "end_time": 864300.0,
      "text": "slow down, stop or swerve."
    },
    {
      "index": 299,
      "start_time": 869220.0,
      "end_time": 871220.0,
      "text": "Let&#39;s see if you would take this next"
    },
    {
      "index": 300,
      "start_time": 871220.0,
      "end_time": 873220.0,
      "text": "opportunity."
    },
    {
      "index": 301,
      "start_time": 890600.0,
      "end_time": 892600.0,
      "text": "Make sure that you&#39;re comfortable"
    },
    {
      "index": 302,
      "start_time": 892881.0,
      "end_time": 894881.0,
      "text": "with your ability to pull away quickly onto"
    },
    {
      "index": 303,
      "start_time": 894881.0,
      "end_time": 896881.0,
      "text": "a roundabout."
    },
    {
      "index": 304,
      "start_time": 899854.0,
      "end_time": 901854.0,
      "text": "The last thing you want to do is pull away quickly only"
    },
    {
      "index": 305,
      "start_time": 901854.0,
      "end_time": 903854.0,
      "text": "to stall."
    },
    {
      "index": 306,
      "start_time": 903854.0,
      "end_time": 905854.0,
      "text": "It&#39;s a bit tricky to see but we made sure"
    },
    {
      "index": 307,
      "start_time": 905854.0,
      "end_time": 907854.0,
      "text": "that the van went first, so that we had a good view."
    },
    {
      "index": 308,
      "start_time": 913670.0,
      "end_time": 915670.0,
      "text": "We&#39;re now approaching a notoriously busy roundabout,"
    },
    {
      "index": 309,
      "start_time": 915670.0,
      "end_time": 917670.0,
      "text": "called the Chinese roundabout."
    },
    {
      "index": 310,
      "start_time": 917670.0,
      "end_time": 919670.0,
      "text": "It&#39;s getting late, getting busy."
    },
    {
      "index": 311,
      "start_time": 920500.0,
      "end_time": 922500.0,
      "text": "Waiting for our opportunity to go."
    },
    {
      "index": 312,
      "start_time": 925448.0,
      "end_time": 927448.0,
      "text": "Which will be this car coming off."
    },
    {
      "index": 313,
      "start_time": 927448.0,
      "end_time": 929448.0,
      "text": "Gives us a chance to get on."
    },
    {
      "index": 314,
      "start_time": 937425.0,
      "end_time": 939425.0,
      "text": "Keep a look out for the opportunity."
    },
    {
      "index": 315,
      "start_time": 939760.0,
      "end_time": 941760.0,
      "text": "Is this car coming off?"
    },
    {
      "index": 316,
      "start_time": 942420.0,
      "end_time": 944420.0,
      "text": "No, they&#39;re coming round."
    },
    {
      "index": 317,
      "start_time": 945302.0,
      "end_time": 947302.0,
      "text": "Also look out for vehicles that will"
    },
    {
      "index": 318,
      "start_time": 947302.0,
      "end_time": 949302.0,
      "text": "give you misleading signals."
    },
    {
      "index": 319,
      "start_time": 949302.0,
      "end_time": 951302.0,
      "text": "Don&#39;t look at their indicators at all."
    },
    {
      "index": 320,
      "start_time": 952360.0,
      "end_time": 954360.0,
      "text": "Use your anticipation skills."
    },
    {
      "index": 321,
      "start_time": 959603.0,
      "end_time": 961603.0,
      "text": "This next car is indicating far too early."
    },
    {
      "index": 322,
      "start_time": 961603.0,
      "end_time": 963603.0,
      "text": "The white van coming off gives us a chance to go."
    },
    {
      "index": 323,
      "start_time": 967960.0,
      "end_time": 969960.0,
      "text": "The next roundabout is in slow motion."
    },
    {
      "index": 324,
      "start_time": 969960.0,
      "end_time": 971960.0,
      "text": "I&#39;m going to leave this next one up to you."
    },
    {
      "index": 325,
      "start_time": 972400.0,
      "end_time": 974400.0,
      "text": "Look out for the opportunity."
    },
    {
      "index": 326,
      "start_time": 976489.0,
      "end_time": 978489.0,
      "text": "3 cars coming round"
    },
    {
      "index": 327,
      "start_time": 978646.0,
      "end_time": 980646.0,
      "text": "which ones coming off?"
    },
    {
      "index": 328,
      "start_time": 992286.0,
      "end_time": 994286.0,
      "text": "Would you of taken that opportunity?"
    },
    {
      "index": 329,
      "start_time": 1031940.0,
      "end_time": 1033940.0,
      "text": "Look out for where they&#39;re steering."
    },
    {
      "index": 330,
      "start_time": 1034599.9999999999,
      "end_time": 1036599.9999999999,
      "text": "Look at their angle."
    },
    {
      "index": 331,
      "start_time": 1038260.0,
      "end_time": 1040260.0,
      "text": "Also, are they speeding up to exit."
    },
    {
      "index": 332,
      "start_time": 1048720.0,
      "end_time": 1050720.0,
      "text": "All aspects of driving can be dangerous"
    },
    {
      "index": 333,
      "start_time": 1051480.0,
      "end_time": 1053480.0,
      "text": "make sure that when you practice roundabouts"
    },
    {
      "index": 334,
      "start_time": 1053480.0,
      "end_time": 1055480.0,
      "text": "that you start somewhere quiet"
    },
    {
      "index": 335,
      "start_time": 1056260.0,
      "end_time": 1058260.0,
      "text": "and at a quiet time and gradually build-up to"
    },
    {
      "index": 336,
      "start_time": 1058260.0,
      "end_time": 1060260.0,
      "text": "this level"
    },
    {
      "index": 337,
      "start_time": 1060260.0,
      "end_time": 1062260.0,
      "text": "which is rush hour traffic."
    },
    {
      "index": 338,
      "start_time": 1062260.0,
      "end_time": 1064260.0,
      "text": "Don&#39;t do anything dangerous."
    },
    {
      "index": 339,
      "start_time": 1069860.0,
      "end_time": 1071860.0,
      "text": "Here the angle of this car"
    },
    {
      "index": 340,
      "start_time": 1071860.0,
      "end_time": 1073860.0,
      "text": "gives me a good idea that they&#39;re coming off."
    },
    {
      "index": 341,
      "start_time": 1074250.0,
      "end_time": 1076250.0,
      "text": "Gives us a great opportunity."
    },
    {
      "index": 342,
      "start_time": 1092840.0,
      "end_time": 1094840.0,
      "text": "This next roundabout"
    },
    {
      "index": 343,
      "start_time": 1095130.0,
      "end_time": 1097130.0,
      "text": "I will deliberately hesitate."
    },
    {
      "index": 344,
      "start_time": 1099980.0,
      "end_time": 1101980.0,
      "text": "There was an opportunity straight away to get on."
    },
    {
      "index": 345,
      "start_time": 1102270.0,
      "end_time": 1104270.0,
      "text": "Let&#39;s see if you spot the next opportunity."
    },
    {
      "index": 346,
      "start_time": 1104270.0,
      "end_time": 1106270.0,
      "text": "That white car came off."
    },
    {
      "index": 347,
      "start_time": 1106270.0,
      "end_time": 1108270.0,
      "text": "Is there another one?"
    },
    {
      "index": 348,
      "start_time": 1127340.0,
      "end_time": 1129340.0,
      "text": "Is there an opportunity?"
    },
    {
      "index": 349,
      "start_time": 1129340.0,
      "end_time": 1131340.0,
      "text": "Would of been a bit too tight."
    },
    {
      "index": 350,
      "start_time": 1131340.0,
      "end_time": 1133340.0,
      "text": "That blue car?"
    },
    {
      "index": 351,
      "start_time": 1133340.0,
      "end_time": 1135340.0,
      "text": "That was a great chance."
    },
    {
      "index": 352,
      "start_time": 1135340.0,
      "end_time": 1137340.0,
      "text": "The 4x4?"
    },
    {
      "index": 353,
      "start_time": 1148300.0,
      "end_time": 1150300.0,
      "text": "That was a good one."
    },
    {
      "index": 354,
      "start_time": 1155220.0,
      "end_time": 1157220.0,
      "text": "Look at how fast that cars going."
    },
    {
      "index": 355,
      "start_time": 1159620.0,
      "end_time": 1161620.0,
      "text": "It&#39;s always a good indication that they&#39;re going to"
    },
    {
      "index": 356,
      "start_time": 1161620.0,
      "end_time": 1163620.0,
      "text": "come off and give us a chance."
    },
    {
      "index": 357,
      "start_time": 1165410.0,
      "end_time": 1167410.0,
      "text": "At this next roundabout"
    },
    {
      "index": 358,
      "start_time": 1167730.0,
      "end_time": 1169730.0,
      "text": "again I&#39;m going to deliberately."
    },
    {
      "index": 359,
      "start_time": 1170880.0,
      "end_time": 1172880.0,
      "text": "Let&#39;s see if you spot the opportunities."
    },
    {
      "index": 360,
      "start_time": 1173800.0,
      "end_time": 1175800.0,
      "text": "There&#39;s one."
    },
    {
      "index": 361,
      "start_time": 1178120.0,
      "end_time": 1180120.0,
      "text": "Another.."
    },
    {
      "index": 362,
      "start_time": 1185140.0,
      "end_time": 1187140.0,
      "text": "Another opportunity..."
    },
    {
      "index": 363,
      "start_time": 1188860.0,
      "end_time": 1190860.0,
      "text": "Another one..."
    },
    {
      "index": 364,
      "start_time": 1203260.0,
      "end_time": 1205260.0,
      "text": "Great chance."
    },
    {
      "index": 365,
      "start_time": 1208700.0,
      "end_time": 1210700.0,
      "text": "As usual look our cyclists"
    },
    {
      "index": 366,
      "start_time": 1211410.0,
      "end_time": 1213410.0,
      "text": "and pedestrians that might be near the roundabout"
    },
    {
      "index": 367,
      "start_time": 1213410.0,
      "end_time": 1215410.0,
      "text": "or on it."
    },
    {
      "index": 368,
      "start_time": 1215540.0,
      "end_time": 1217540.0,
      "text": "This time, our view is blocked by this van."
    },
    {
      "index": 369,
      "start_time": 1217540.0,
      "end_time": 1219540.0,
      "text": "So we need to make sure that we can see behind it."
    },
    {
      "index": 370,
      "start_time": 1219540.0,
      "end_time": 1221540.0,
      "text": "It&#39;s all clear and we can go."
    },
    {
      "index": 371,
      "start_time": 1221540.0,
      "end_time": 1223540.0,
      "text": "Wow! That was a lot of roundabouts!"
    },
    {
      "index": 372,
      "start_time": 1225570.0,
      "end_time": 1227570.0,
      "text": "We&#39;ve shown you big roundabouts, mini ones and opportunities when to"
    },
    {
      "index": 373,
      "start_time": 1227570.0,
      "end_time": 1229570.0,
      "text": "get going onto a roundabout."
    },
    {
      "index": 374,
      "start_time": 1229570.0,
      "end_time": 1231570.0,
      "text": "We really hope this video"
    },
    {
      "index": 375,
      "start_time": 1231570.0,
      "end_time": 1233570.0,
      "text": "has been useful"
    },
    {
      "index": 376,
      "start_time": 1233570.0,
      "end_time": 1235570.0,
      "text": "if it has, then please give us a &#39;thumbs up&#39;"
    },
    {
      "index": 377,
      "start_time": 1235570.0,
      "end_time": 1237570.0,
      "text": "like at the bottom of the screen"
    },
    {
      "index": 378,
      "start_time": 1237570.0,
      "end_time": 1239570.0,
      "text": "and share your experiences of roundabouts"
    },
    {
      "index": 379,
      "start_time": 1239570.0,
      "end_time": 1241570.0,
      "text": "in the comments section below."
    },
    {
      "index": 380,
      "start_time": 1241570.0,
      "end_time": 1243570.0,
      "text": "Don&#39;t forget driving is very dangerous"
    },
    {
      "index": 381,
      "start_time": 1243570.0,
      "end_time": 1245570.0,
      "text": "so make sure that you get help and"
    },
    {
      "index": 382,
      "start_time": 1245570.0,
      "end_time": 1247570.0,
      "text": "guidance from a professional driving instructor"
    },
    {
      "index": 383,
      "start_time": 1247570.0,
      "end_time": 1249570.0,
      "text": "and hopefully we&#39;ll see you on the next video!"
    },
    {
      "index": 384,
      "start_time": 1249570.0,
      "end_time": 1251570.0,
      "text": "Thanks again for watching."
    }
  ]
}